{
    "classification": "electronic",
    "type": "led",
    "size": "10_mm",
    "color": "blue",
    "description_main": "",
    "description_extra": "",
    "manufacturer": "",
    "part_number": "",
    "from_yaml": false,
    "make_files": true,
    "filter": "",
    "kicad_reference": "L",
    "classification_upper": "ELECTRONIC",
    "classification_capital": "Electronic",
    "classification_first_letter": "e",
    "classification_first_letter_upper": "E",
    "type_upper": "LED",
    "type_capital": "Led",
    "type_first_letter": "l",
    "type_first_letter_upper": "L",
    "size_upper": "10_MM",
    "size_capital": "10 mm",
    "size_first_letter": "1",
    "size_first_letter_upper": "1",
    "color_upper": "BLUE",
    "color_capital": "Blue",
    "color_first_letter": "b",
    "color_first_letter_upper": "B",
    "description_main_upper": "",
    "description_main_capital": "",
    "description_main_first_letter": "",
    "description_main_first_letter_upper": "",
    "description_extra_upper": "",
    "description_extra_capital": "",
    "description_extra_first_letter": "",
    "description_extra_first_letter_upper": "",
    "manufacturer_upper": "",
    "manufacturer_capital": "",
    "manufacturer_first_letter": "",
    "manufacturer_first_letter_upper": "",
    "part_number_upper": "",
    "part_number_capital": "",
    "part_number_first_letter": "",
    "part_number_first_letter_upper": "",
    "id": "electronic_led_10_mm_blue",
    "id_no_class": "led_10_mm_blue",
    "id_no_type": "10_mm_blue",
    "id_no_size": "blue",
    "oomp_key": "oomp_electronic_led_10_mm_blue",
    "github_link": "https://github.com/oomlout/oomlout_oomp_part_src/tree/main/parts/electronic_led_10_mm_blue/working",
    "directory": "parts/electronic_led_10_mm_blue",
    "name": "Electronic Led 10 Mm Blue",
    "name_no_class": "Led 10 Mm Blue",
    "name_no_type": "10 Mm Blue",
    "name_no_size": "Blue",
    "short_code": "l10l",
    "short_code_upper": "L10L",
    "short_name": "10 Mm Blue Led",
    "distributors": [],
    "manufacturers": [],
    "md5": "78055f06d160820fbae0757e8a0f65f1",
    "md5_5": "78055",
    "md5_5_upper": "78055",
    "md5_6": "78055f",
    "md5_6_upper": "78055F",
    "md5_6_alpha": "4ol7j",
    "md5_6_alpha_upper": "4OL7J",
    "md5_10": "78055f06d1",
    "md5_10_upper": "78055F06D1",
    "oomp_word": "bell kissing leopard",
    "oomp_word_list": [
        "bell",
        "kissing",
        "leopard"
    ],
    "oomp_word_emoji": ":bell: :kissing: :leopard:",
    "oomp_word_emoji_list": [
        ":bell:",
        ":kissing:",
        ":leopard:"
    ],
    "size_only_numbers": "10",
    "size_only_numbers_no_zeros": "1",
    "description_only_numbers": "",
    "description_only_numbers_short": " ",
    "name_no_size_short": "Blue",
    "description_or_color": "B ",
    "description_or_color_upper": "B ",
    "markdown_full": "[electronic_led_10_mm_blue](https://github.com/oomlout/oomlout_oomp_part_src/tree/main/parts/electronic_led_10_mm_blue/working)<br>[l10l](https://github.com/oomlout/oomlout_oomp_part_src/tree/main/parts/electronic_led_10_mm_blue/working)<br>[Electronic Led 10 Mm Blue](https://github.com/oomlout/oomlout_oomp_part_src/tree/main/parts/electronic_led_10_mm_blue/working)<br><br>",
    "markdown_short": "[electronic_led_10_mm_blue](https://github.com/oomlout/oomlout_oomp_part_src/tree/main/parts/electronic_led_10_mm_blue/working)<br><br>"
}