{
    "classification": "electronic",
    "type": "socket",
    "size": "2_54_mm",
    "color": "",
    "description_main": "9_pin",
    "description_extra": "through_hole_long",
    "manufacturer": "",
    "part_number": "",
    "make_files": true,
    "kicad_reference": "CONN",
    "classification_upper": "ELECTRONIC",
    "classification_capital": "Electronic",
    "classification_first_letter": "e",
    "classification_first_letter_upper": "E",
    "type_upper": "SOCKET",
    "type_capital": "Socket",
    "type_first_letter": "s",
    "type_first_letter_upper": "S",
    "size_upper": "2_54_MM",
    "size_capital": "2.54 mm",
    "size_first_letter": "2",
    "size_first_letter_upper": "2",
    "color_upper": "",
    "color_capital": "",
    "color_first_letter": "",
    "color_first_letter_upper": "",
    "description_main_upper": "9_PIN",
    "description_main_capital": "9 Pin",
    "description_main_first_letter": "9",
    "description_main_first_letter_upper": "9",
    "description_extra_upper": "THROUGH_HOLE_LONG",
    "description_extra_capital": "Through Hole Long",
    "description_extra_first_letter": "t",
    "description_extra_first_letter_upper": "T",
    "manufacturer_upper": "",
    "manufacturer_capital": "",
    "manufacturer_first_letter": "",
    "manufacturer_first_letter_upper": "",
    "part_number_upper": "",
    "part_number_capital": "",
    "part_number_first_letter": "",
    "part_number_first_letter_upper": "",
    "id": "electronic_socket_2_54_mm_9_pin_through_hole_long",
    "id_no_class": "socket_2_54_mm_9_pin_through_hole_long",
    "id_no_type": "2_54_mm_9_pin_through_hole_long",
    "id_no_size": "9_pin_through_hole_long",
    "oomp_key": "oomp_electronic_socket_2_54_mm_9_pin_through_hole_long",
    "github_link": "https://github.com/oomlout/oomlout_oomp_part_src/tree/main/parts/electronic_socket_2_54_mm_9_pin_through_hole_long/working",
    "directory": "parts/electronic_socket_2_54_mm_9_pin_through_hole_long",
    "name": "Electronic Socket 2 54 Mm 9 Pin Through Hole Long",
    "name_no_class": "Socket 2 54 Mm 9 Pin Through Hole Long",
    "name_no_type": "2 54 Mm 9 Pin Through Hole Long",
    "name_no_size": "9 Pin Through Hole Long",
    "short_code": "sci19pthl",
    "short_code_upper": "SCI19PTHL",
    "distributors": [],
    "manufacturers": [],
    "md5": "cdd8e6bbcab8b243c4af68047c9e464d",
    "md5_5": "cdd8e",
    "md5_5_upper": "CDD8E",
    "md5_6": "cdd8e6",
    "md5_6_upper": "CDD8E6",
    "md5_6_alpha": "8159i",
    "md5_6_alpha_upper": "8159I",
    "md5_10": "cdd8e6bbca",
    "md5_10_upper": "CDD8E6BBCA",
    "oomp_word": "strawberry hospital airplane",
    "oomp_word_list": [
        "strawberry",
        "hospital",
        "airplane"
    ],
    "oomp_word_emoji": ":strawberry: :hospital: :airplane:",
    "oomp_word_emoji_list": [
        ":strawberry:",
        ":hospital:",
        ":airplane:"
    ],
    "size_only_numbers": "254",
    "size_only_numbers_no_zeros": "254",
    "description_only_numbers": "9",
    "description_only_numbers_short": "9",
    "name_no_size_short": "9 Pin Through Hole Long",
    "description_or_color": "9",
    "description_or_color_upper": "9",
    "markdown_full": "[electronic_socket_2_54_mm_9_pin_through_hole_long](https://github.com/oomlout/oomlout_oomp_part_src/tree/main/parts/electronic_socket_2_54_mm_9_pin_through_hole_long/working)<br>[sci19pthl](https://github.com/oomlout/oomlout_oomp_part_src/tree/main/parts/electronic_socket_2_54_mm_9_pin_through_hole_long/working)<br>[Electronic Socket 2 54 Mm 9 Pin Through Hole Long](https://github.com/oomlout/oomlout_oomp_part_src/tree/main/parts/electronic_socket_2_54_mm_9_pin_through_hole_long/working)<br><br>",
    "markdown_short": "[electronic_socket_2_54_mm_9_pin_through_hole_long](https://github.com/oomlout/oomlout_oomp_part_src/tree/main/parts/electronic_socket_2_54_mm_9_pin_through_hole_long/working)<br><br>"
}