{
    "classification": "electronic",
    "type": "led",
    "size": "0201",
    "color": "red",
    "description_main": "",
    "description_extra": "",
    "manufacturer": "",
    "part_number": "",
    "from_yaml": false,
    "make_files": true,
    "filter": "",
    "kicad_reference": "L",
    "classification_upper": "ELECTRONIC",
    "classification_capital": "Electronic",
    "classification_first_letter": "e",
    "classification_first_letter_upper": "E",
    "type_upper": "LED",
    "type_capital": "Led",
    "type_first_letter": "l",
    "type_first_letter_upper": "L",
    "size_upper": "0201",
    "size_capital": "0201",
    "size_first_letter": "0",
    "size_first_letter_upper": "0",
    "color_upper": "RED",
    "color_capital": "Red",
    "color_first_letter": "r",
    "color_first_letter_upper": "R",
    "description_main_upper": "",
    "description_main_capital": "",
    "description_main_first_letter": "",
    "description_main_first_letter_upper": "",
    "description_extra_upper": "",
    "description_extra_capital": "",
    "description_extra_first_letter": "",
    "description_extra_first_letter_upper": "",
    "manufacturer_upper": "",
    "manufacturer_capital": "",
    "manufacturer_first_letter": "",
    "manufacturer_first_letter_upper": "",
    "part_number_upper": "",
    "part_number_capital": "",
    "part_number_first_letter": "",
    "part_number_first_letter_upper": "",
    "id": "electronic_led_0201_red",
    "id_no_class": "led_0201_red",
    "id_no_type": "0201_red",
    "id_no_size": "red",
    "oomp_key": "oomp_electronic_led_0201_red",
    "github_link": "https://github.com/oomlout/oomlout_oomp_part_src/tree/main/parts/electronic_led_0201_red/working",
    "directory": "parts/electronic_led_0201_red",
    "name": "Electronic Led 0201 Red",
    "name_no_class": "Led 0201 Red",
    "name_no_type": "0201 Red",
    "name_no_size": "Red",
    "short_code": "lr",
    "short_code_upper": "LR",
    "short_name": "0201 Red Led",
    "distributors": [],
    "manufacturers": [],
    "md5": "0a5fb3aebfea3215d424df51e0177a19",
    "md5_5": "0a5fb",
    "md5_5_upper": "0A5FB",
    "md5_6": "0a5fb3",
    "md5_6_upper": "0A5FB3",
    "md5_6_alpha": "ekkz",
    "md5_6_alpha_upper": "EKKZ",
    "md5_10": "0a5fb3aebf",
    "md5_10_upper": "0A5FB3AEBF",
    "oomp_word": "sleepy leopard eyeglasses",
    "oomp_word_list": [
        "sleepy",
        "leopard",
        "eyeglasses"
    ],
    "oomp_word_emoji": ":sleepy: :leopard: :eyeglasses:",
    "oomp_word_emoji_list": [
        ":sleepy:",
        ":leopard:",
        ":eyeglasses:"
    ],
    "size_only_numbers": "0201",
    "size_only_numbers_no_zeros": "21",
    "description_only_numbers": "",
    "description_only_numbers_short": " ",
    "name_no_size_short": "Red",
    "description_or_color": "R ",
    "description_or_color_upper": "R ",
    "markdown_full": "[electronic_led_0201_red](https://github.com/oomlout/oomlout_oomp_part_src/tree/main/parts/electronic_led_0201_red/working)<br>[lr](https://github.com/oomlout/oomlout_oomp_part_src/tree/main/parts/electronic_led_0201_red/working)<br>[Electronic Led 0201 Red](https://github.com/oomlout/oomlout_oomp_part_src/tree/main/parts/electronic_led_0201_red/working)<br><br>",
    "markdown_short": "[electronic_led_0201_red](https://github.com/oomlout/oomlout_oomp_part_src/tree/main/parts/electronic_led_0201_red/working)<br><br>"
}